converter/__init__.py
converter/convert.py
amrita_converter-0.1.0.dist-info/LICENSE
amrita_converter-0.1.0.dist-info/METADATA
amrita_converter-0.1.0.dist-info/WHEEL
amrita_converter-0.1.0.dist-info/top_level.txt
amrita_converter-0.1.0.dist-info/RECORD
